LICENSE.txt
README.md
setup.cfg
setup.py
NLPContractions/__init__.py
NLPContractions/contraction.py
NLPContractions.egg-info/PKG-INFO
NLPContractions.egg-info/SOURCES.txt
NLPContractions.egg-info/dependency_links.txt
NLPContractions.egg-info/not-zip-safe
NLPContractions.egg-info/top_level.txt