Metadata-Version: 1.0
Name: NLPContractions
Version: 0.1
Summary: A Python package to replace some english words with their shorter versions (contractions) in a sentence to help text augmentation in NLP tasks
Home-page: https://github.com/vatsalsaglani/nlp-text-contractions.git
Author: Vatsal Saglani
Author-email: UNKNOWN
License: MIT
Platform: UNKNOWN
